configjy/ConfigFile.py
configjy/__init__.py
configjy-0.1.0.6.dist-info/LICENSE
configjy-0.1.0.6.dist-info/METADATA
configjy-0.1.0.6.dist-info/WHEEL
configjy-0.1.0.6.dist-info/RECORD
