Metadata-Version: 2.1
Name: configjy
Version: 0.1.0.6
Summary: Loads a json or yaml config file
Author: henrique lino
Author-email: henrique.lino97@gmail.com
Requires-Python: >=3.9,<4.0
Classifier: Programming Language :: Python :: 3
Classifier: Programming Language :: Python :: 3.9
Classifier: Programming Language :: Python :: 3.10
Classifier: Programming Language :: Python :: 3.11
Requires-Dist: ruamel.yaml (>=0.17.21,<0.18.0)
